mt/sql/__init__.py
mt/sql/base.py
mt/sql/mysql.py
mt/sql/psql.py
mt/sql/sqlite.py
mt/sql/version.py
mt/sql/redshift/__init__.py
mt/sql/redshift/commands.py
mt/sql/redshift/ddl.py
mt/sql/redshift/dialect.py
mt/sql/redshift/main.py
mt/sql/redshift/redshift-ca-bundle.crt
mtsql-1.12.32.dist-info/licenses/LICENSE
mtsql-1.12.32.dist-info/METADATA
mtsql-1.12.32.dist-info/WHEEL
mtsql-1.12.32.dist-info/top_level.txt
mtsql-1.12.32.dist-info/RECORD
