Metadata-Version: 2.4
Name: mtsql
Version: 1.12.32
Summary: Extra Python modules to deal with the interaction between pandas dataframes and remote SQL servers, for Minh-Tri Pham
Home-page: https://github.com/inteplus/mtsql
Author: Minh-Tri Pham
Project-URL: Documentation, https://mtdoc.readthedocs.io/en/latest/mt.sql/mt.sql.html
Project-URL: Source Code, https://github.com/inteplus/mtsql
License-File: LICENSE
Requires-Dist: sqlalchemy
Requires-Dist: tzlocal
Requires-Dist: tqdm
Requires-Dist: psycopg[binary]
Requires-Dist: redshift_connector>=2.1.5
Requires-Dist: mtbase>=4.3.2
Requires-Dist: mtpandas>=1.17.16
Dynamic: author
Dynamic: home-page
Dynamic: license-file
Dynamic: project-url
Dynamic: requires-dist
Dynamic: summary
